i_impute-1.0.6.dist-info/METADATA
i_impute-1.0.6.dist-info/RECORD
i_impute-1.0.6.dist-info/WHEEL
i_impute-1.0.6.dist-info/top_level.txt
iimpute/__init__.py
iimpute/iimpute.py
iimpute/utils.py
iimpute/version.py
