Metadata-Version: 2.1
Name: i-impute
Version: 1.0.6
Summary: I-Impute: a self-consistent method to impute single cell RNA sequencing data
Home-page: https://github.com/xikanfeng2/I-Impute
Author: Xikang Feng
Author-email: xikanfeng2@gmail.com
License: UNKNOWN
Platform: UNKNOWN
Classifier: Programming Language :: Python :: 3
Classifier: License :: OSI Approved :: MIT License
Classifier: Operating System :: OS Independent
